wkr/__init__.py
wkr/compat.py
wkr/io.py
wkr/os.py
wkr/pd.py
wkr-1.0.3.dist-info/AUTHORS.rst
wkr-1.0.3.dist-info/LICENSE
wkr-1.0.3.dist-info/METADATA
wkr-1.0.3.dist-info/WHEEL
wkr-1.0.3.dist-info/top_level.txt
wkr-1.0.3.dist-info/RECORD
