Metadata-Version: 2.1
Name: wkr
Version: 1.0.3
Summary: Python utility library
Home-page: https://github.com/wroberts/wkr.py
Author: Will Roberts
Author-email: wildwilhelm@gmail.com
License: MIT license
Keywords: wkr
Platform: UNKNOWN
Classifier: Development Status :: 2 - Pre-Alpha
Classifier: Intended Audience :: Developers
Classifier: License :: OSI Approved :: MIT License
Classifier: Natural Language :: English
Classifier: Programming Language :: Python :: 2
Classifier: Programming Language :: Python :: 2.7
Classifier: Programming Language :: Python :: 3
Classifier: Programming Language :: Python :: 3.5
Classifier: Programming Language :: Python :: 3.6
